aurora_dsql_django/__init__.py
aurora_dsql_django/_version.py
aurora_dsql_django/base.py
aurora_dsql_django/creation.py
aurora_dsql_django/features.py
aurora_dsql_django/operations.py
aurora_dsql_django/py.typed
aurora_dsql_django/schema.py
aurora_dsql_django/tests/__init__.py
aurora_dsql_django/tests/test_settings.py
aurora_dsql_django/tests/utils.py
aurora_dsql_django/tests/integration/__init__.py
aurora_dsql_django/tests/integration/test_dsql.py
aurora_dsql_django/tests/unit/__init__.py
aurora_dsql_django/tests/unit/test_base.py
aurora_dsql_django/tests/unit/test_creation.py
aurora_dsql_django/tests/unit/test_features.py
aurora_dsql_django/tests/unit/test_operations.py
aurora_dsql_django/tests/unit/test_schema.py
aurora_dsql_django/tests/unit/test_wrapper.py
aurora_dsql_django-0.4.1.dist-info/METADATA
aurora_dsql_django-0.4.1.dist-info/WHEEL
aurora_dsql_django-0.4.1.dist-info/RECORD
