Metadata-Version: 2.4
Name: aurora_dsql_django
Version: 0.4.1
Summary: Aurora DSQL adapter for Django
Project-URL: Repository, https://github.com/awslabs/aurora-dsql-orms
Project-URL: Documentation, https://github.com/awslabs/aurora-dsql-orms/tree/main/python/django
Author: Amazon Web Services
License-Expression: Apache-2.0
Classifier: Framework :: Django
Classifier: Framework :: Django :: 4.2
Classifier: Framework :: Django :: 5.0
Classifier: Framework :: Django :: 5.1
Classifier: Framework :: Django :: 5.2
Classifier: Intended Audience :: Developers
Classifier: License :: OSI Approved :: Apache Software License
Classifier: Programming Language :: Python
Classifier: Programming Language :: Python :: 3.10
Classifier: Programming Language :: Python :: 3.11
Classifier: Programming Language :: Python :: 3.12
Classifier: Programming Language :: Python :: 3.13
Requires-Python: >=3.10
Requires-Dist: aurora-dsql-python-connector>=0.1.0
